router_maestro/__init__.py
router_maestro/__main__.py
router_maestro/auth/__init__.py
router_maestro/auth/github_oauth.py
router_maestro/auth/manager.py
router_maestro/auth/storage.py
router_maestro/cli/__init__.py
router_maestro/cli/auth.py
router_maestro/cli/client.py
router_maestro/cli/config.py
router_maestro/cli/context.py
router_maestro/cli/main.py
router_maestro/cli/model.py
router_maestro/cli/server.py
router_maestro/config/__init__.py
router_maestro/config/contexts.py
router_maestro/config/paths.py
router_maestro/config/priorities.py
router_maestro/config/providers.py
router_maestro/config/server.py
router_maestro/config/settings.py
router_maestro/providers/__init__.py
router_maestro/providers/anthropic.py
router_maestro/providers/base.py
router_maestro/providers/copilot.py
router_maestro/providers/openai.py
router_maestro/providers/openai_compat.py
router_maestro/routing/__init__.py
router_maestro/routing/router.py
router_maestro/server/__init__.py
router_maestro/server/app.py
router_maestro/server/oauth_sessions.py
router_maestro/server/translation.py
router_maestro/server/middleware/__init__.py
router_maestro/server/middleware/auth.py
router_maestro/server/routes/__init__.py
router_maestro/server/routes/admin.py
router_maestro/server/routes/anthropic.py
router_maestro/server/routes/chat.py
router_maestro/server/routes/models.py
router_maestro/server/schemas/__init__.py
router_maestro/server/schemas/admin.py
router_maestro/server/schemas/anthropic.py
router_maestro/server/schemas/openai.py
router_maestro/utils/__init__.py
router_maestro/utils/logging.py
router_maestro/utils/tokens.py
router_maestro-0.1.5.dist-info/METADATA
router_maestro-0.1.5.dist-info/WHEEL
router_maestro-0.1.5.dist-info/entry_points.txt
router_maestro-0.1.5.dist-info/licenses/LICENSE
router_maestro-0.1.5.dist-info/RECORD
