Metadata-Version: 2.4
Name: router-maestro
Version: 0.1.5
Summary: Multi-model routing and load balancing system with OpenAI-compatible API
Author-email: Kanwen Li <likanwen@icloud.com>
License-Expression: MIT
License-File: LICENSE
Keywords: api,copilot,llm,load-balancing,openai,routing
Classifier: Development Status :: 3 - Alpha
Classifier: Environment :: Console
Classifier: Intended Audience :: Developers
Classifier: License :: OSI Approved :: MIT License
Classifier: Programming Language :: Python :: 3
Classifier: Programming Language :: Python :: 3.11
Classifier: Programming Language :: Python :: 3.12
Classifier: Topic :: Software Development :: Libraries :: Python Modules
Requires-Python: >=3.11
Requires-Dist: aiosqlite>=0.19.0
Requires-Dist: anthropic>=0.40.0
Requires-Dist: authlib>=1.3.0
Requires-Dist: fastapi>=0.109.0
Requires-Dist: httpx>=0.26.0
Requires-Dist: plotext>=5.2.0
Requires-Dist: pydantic-settings>=2.1.0
Requires-Dist: pydantic>=2.5.0
Requires-Dist: python-dotenv>=1.0.0
Requires-Dist: rich>=13.7.0
Requires-Dist: tiktoken>=0.5.0
Requires-Dist: typer>=0.12.0
Requires-Dist: uvicorn>=0.27.0
Provides-Extra: dev
Requires-Dist: pyinstaller>=6.3.0; extra == 'dev'
Requires-Dist: pytest-asyncio>=0.23.0; extra == 'dev'
Requires-Dist: pytest>=7.4.0; extra == 'dev'
Requires-Dist: ruff>=0.1.0; extra == 'dev'
